ourtransform/__init__.py
ourtransform/framework.py
ourtransform/utils.py
tests/__init__.py
tests/fake_logger.py
tests/test_framework.py
tests/test_framework_async.py
tests/test_special_cases.py
tests/test_transform_subclass.py
ourtransform-0.0.5.dist-info/LICENSE
ourtransform-0.0.5.dist-info/METADATA
ourtransform-0.0.5.dist-info/WHEEL
ourtransform-0.0.5.dist-info/top_level.txt
ourtransform-0.0.5.dist-info/RECORD
