Metadata-Version: 2.1
Name: ourtransform
Version: 0.0.5
Summary: Tools for transforming one data structure to another, quick and simple.
Home-page: UNKNOWN
Author: Rikard Olsson
Author-email: rikard@ourstudio.se
License: UNKNOWN
Platform: UNKNOWN
Requires-Dist: numpy (>=1.19.5)
